pyramid_kvs2-2.1.1.dist-info/METADATA
pyramid_kvs2-2.1.1.dist-info/WHEEL
pyramid_kvs2-2.1.1.dist-info/entry_points.txt
pyramid_kvs2-2.1.1.dist-info/licenses/LICENSE
pyramid_kvs2/__init__.py
pyramid_kvs2/cache.py
pyramid_kvs2/kvs.py
pyramid_kvs2/py.typed
pyramid_kvs2/ratelimit.py
pyramid_kvs2/serializer.py
pyramid_kvs2/session.py
pyramid_kvs2/testing.py
pyramid_kvs2/typing.py
pyramid_kvs2-2.1.1.dist-info/RECORD
