Metadata-Version: 2.1
Name: pyramid-kvs2
Version: 2.1.1
Summary: Session and cache for Pyramid
Author-Email: Gandi <tech@gandi.net>
License: GNU
Classifier: Programming Language :: Python
Classifier: Programming Language :: Python :: 3
Classifier: Programming Language :: Python :: 3.7
Classifier: Programming Language :: Python :: 3.8
Classifier: Programming Language :: Python :: 3.9
Classifier: Programming Language :: Python :: 3.10
Classifier: Programming Language :: Python :: 3.11
Classifier: Programming Language :: Python :: 3.12
Classifier: Programming Language :: Python :: 3.13
Classifier: Framework :: Pyramid
Classifier: Topic :: Internet :: WWW/HTTP
Classifier: Topic :: Internet :: WWW/HTTP :: WSGI
Classifier: License :: OSI Approved :: GNU General Public License v2 (GPLv2)
Classifier: Typing :: Typed
Project-URL: Homepage, https://github.com/mardiros/pyramid-kvs2
Project-URL: Documentation, https://github.com/mardiros/pyramid-kvs2/blob/main/README.rst
Project-URL: Repository, https://github.com/mardiros/pyramid-kvs2.git
Project-URL: Issues, https://github.com/mardiros/pyramid-kvs2/issues
Project-URL: Changelog, https://github.com/mardiros/pyramid-kvs2/blob/main/CHANGES.rst
Requires-Python: >=3.7
Requires-Dist: pyramid<3,>=1.10.0
Requires-Dist: redis<6.0,>=4.0
Requires-Dist: python3-memcached>=1.50
Requires-Dist: importlib_metadata; python_version < "3.8"
Requires-Dist: typing-extensions>=4.7.1
